gfb/__init__.py
gfb/app.py
gfb/configuration.py
gfb/git.py
gfb/userinput.py
gfb-0.9b4.dist-info/DESCRIPTION.rst
gfb-0.9b4.dist-info/METADATA
gfb-0.9b4.dist-info/RECORD
gfb-0.9b4.dist-info/WHEEL
gfb-0.9b4.dist-info/entry_points.txt
gfb-0.9b4.dist-info/metadata.json
gfb-0.9b4.dist-info/top_level.txt
