Metadata-Version: 2.0
Name: gfb
Version: 0.9b4
Summary: Find branches in a remote github repository
Home-page: https://github.com/barnardn/gfb
Author: Norm Barnard
Author-email: norm@normbarnard.com
License: MIT
Keywords: git github branch branches find search
Platform: UNKNOWN
Classifier: Development Status :: 4 - Beta
Classifier: License :: OSI Approved :: MIT License
Classifier: Programming Language :: Python :: 3.5
Classifier: Programming Language :: Python :: 3.6
Classifier: Topic :: Utilities
Requires-Python: ~=3.5
Requires-Dist: pygithub
Requires-Dist: pyjwt
Requires-Dist: readchar
